MANIFEST.in
setup.py
tox.ini
flask_simple_api/__init__.py
flask_simple_api/__version__.py
flask_simple_api/simple_api.py
flask_simple_api.egg-info/PKG-INFO
flask_simple_api.egg-info/SOURCES.txt
flask_simple_api.egg-info/dependency_links.txt
flask_simple_api.egg-info/namespace_packages.txt
flask_simple_api.egg-info/requires.txt
flask_simple_api.egg-info/top_level.txt
tests/__init__.py
tests/conftest.py
tests/test_api.py