Metadata-Version: 1.1
Name: flask-simple-api
Version: 1.4.0
Summary: Simple API endpoints for Flask using Flask-Restful reqparse and Python 3 annotations
Home-page: https://github.com/vmalloc/flask-simple-api
Author: Rotem Yaari
Author-email: vmalloc@gmail.com
License: BSD3
Platform: UNKNOWN
Classifier: Programming Language :: Python :: 3.3
Classifier: Programming Language :: Python :: 3.4
